collective.wfadaptations-2.0.0a1-py3.13-nspkg.pth
collective/wfadaptations/__init__.py
collective/wfadaptations/api.py
collective/wfadaptations/configure.zcml
collective/wfadaptations/example.py
collective/wfadaptations/example.zcml
collective/wfadaptations/interfaces.py
collective/wfadaptations/setuphandlers.py
collective/wfadaptations/testing.py
collective/wfadaptations/testing.zcml
collective/wfadaptations/vocabularies.py
collective/wfadaptations/vocabularies.zcml
collective/wfadaptations/wfadaptation.py
collective/wfadaptations/browser/__init__.py
collective/wfadaptations/browser/configure.zcml
collective/wfadaptations/browser/list_adaptations.py
collective/wfadaptations/browser/settings.py
collective/wfadaptations/browser/static/.gitkeep
collective/wfadaptations/browser/templates/associate_workflow_adaptation.pt
collective/wfadaptations/browser/templates/list_workflow_adaptations.pt
collective/wfadaptations/browser/templates/manage_workflow_adaptations.pt
collective/wfadaptations/content/__init__.py
collective/wfadaptations/content/configure.zcml
collective/wfadaptations/locales/fr/LC_MESSAGES/collective.wfadaptations.po
collective/wfadaptations/profiles/default/browserlayer.xml
collective/wfadaptations/profiles/default/collectivewfadaptations_marker.txt
collective/wfadaptations/profiles/default/controlpanel.xml
collective/wfadaptations/profiles/default/metadata.xml
collective/wfadaptations/profiles/default/registry.xml
collective/wfadaptations/profiles/uninstall/browserlayer.xml
collective/wfadaptations/profiles/uninstall/collectivewfadaptations_uninstall_marker.txt
collective/wfadaptations/profiles/uninstall/controlpanel.xml
collective/wfadaptations/profiles/uninstall/registry.xml
collective/wfadaptations/tests/__init__.py
collective/wfadaptations/tests/base.py
collective/wfadaptations/tests/test_api.py
collective/wfadaptations/tests/test_associate.py
collective/wfadaptations/tests/test_robot.py
collective/wfadaptations/tests/test_setup.py
collective_wfadaptations-2.0.0a1.dist-info/METADATA
collective_wfadaptations-2.0.0a1.dist-info/WHEEL
collective_wfadaptations-2.0.0a1.dist-info/entry_points.txt
collective_wfadaptations-2.0.0a1.dist-info/namespace_packages.txt
collective_wfadaptations-2.0.0a1.dist-info/top_level.txt
collective_wfadaptations-2.0.0a1.dist-info/RECORD
